clap/__init__.py
clap/__init__.pyi
clap/api.py
clap/core.py
clap/diagnostics.py
clap/help.py
clap/parser.py
clap/styling.py
typed_clap-0.11.1.dist-info/WHEEL
typed_clap-0.11.1.dist-info/entry_points.txt
typed_clap-0.11.1.dist-info/METADATA
typed_clap-0.11.1.dist-info/RECORD
