Metadata-Version: 2.4
Name: typed-clap
Version: 0.11.1
Summary: A declarative and type-safe command-line argument parser.
Keywords: clap,command-line,argument,cli,parser,argparse,declarative,derive,typed
Author: Aditya Singh
Author-email: Aditya Singh <1adityasingh@proton.me>
License-Expression: MIT
Classifier: Development Status :: 4 - Beta
Classifier: Intended Audience :: Developers
Classifier: License :: OSI Approved :: MIT License
Classifier: Programming Language :: Python :: 3.13
Classifier: Programming Language :: Python :: 3.14
Classifier: Topic :: Software Development :: Libraries
Classifier: Typing :: Typed
Maintainer: Aditya Singh
Maintainer-email: Aditya Singh <1adityasingh@proton.me>
Requires-Python: >=3.13
Project-URL: Changelog, https://github.com/adityasz/typed-clap/blob/master/CHANGELOG.md
Project-URL: Documentation, https://adityasz.github.io/typed-clap
Project-URL: Homepage, https://github.com/adityasz/typed-clap
Project-URL: Issues, https://github.com/adityasz/typed-clap/issues
Project-URL: Repository, https://github.com/adityasz/typed-clap.git
